pandas_ollama/__init__.py
pandas_ollama/api.py
pandas_ollama/colab_adapter.py
pandas_ollama/config.py
pandas_ollama/core.py
pandas_ollama/history.py
pandas_ollama/requirements.txt
pandas_ollama/response.py
pandas_ollama/transformations.py
pandas_ollama/visualizations.py
pandas_ollama-1.0.3.dist-info/licenses/LICENSE
pandas_ollama-1.0.3.dist-info/METADATA
pandas_ollama-1.0.3.dist-info/WHEEL
pandas_ollama-1.0.3.dist-info/top_level.txt
pandas_ollama-1.0.3.dist-info/RECORD
