Metadata-Version: 2.4
Name: pandas-ollama
Version: 1.0.3
Summary: Natural language interface for pandas DataFrame analysis using Ollama models
Home-page: https://github.com/emredeveloper/pandas-ollama
Author: Cihat Emre Karata
Author-email: chtemrekrts@gmail.com
Project-URL: Bug Reports, https://github.com/emredeveloper/pandas-ollama/issues
Project-URL: Source, https://github.com/emredeveloper/pandas-ollama
Keywords: pandas,ollama,ai,dataframe,analysis,visualization,natural language
Classifier: Programming Language :: Python :: 3
Classifier: License :: OSI Approved :: MIT License
Classifier: Operating System :: OS Independent
Classifier: Topic :: Scientific/Engineering :: Artificial Intelligence
Classifier: Topic :: Scientific/Engineering :: Visualization
Classifier: Topic :: Software Development :: Libraries :: Python Modules
Requires-Python: >=3.8
License-File: LICENSE
Requires-Dist: pandas>=1.3.0
Requires-Dist: requests>=2.25.0
Requires-Dist: matplotlib>=3.4.0
Requires-Dist: seaborn>=0.11.0
Requires-Dist: json5>=0.9.5
Requires-Dist: typing-extensions>=4.0.0
Requires-Dist: numpy>=1.20.0
Requires-Dist: pillow>=8.0.0
Dynamic: author
Dynamic: author-email
Dynamic: classifier
Dynamic: description
Dynamic: description-content-type
Dynamic: home-page
Dynamic: keywords
Dynamic: license-file
Dynamic: project-url
Dynamic: requires-dist
Dynamic: requires-python
Dynamic: summary
